tistory_indexer/__about__.py
tistory_indexer/__init__.py
tistory_indexer/indexer.py
tistory_indexer-0.1.3.dist-info/METADATA
tistory_indexer-0.1.3.dist-info/WHEEL
tistory_indexer-0.1.3.dist-info/licenses/LICENSE
tistory_indexer-0.1.3.dist-info/RECORD
