Metadata-Version: 2.4
Name: tistory-indexer
Version: 0.1.3
Summary: Submit and check indexing status of Tistory blog posts via Google's Indexing API
Project-URL: Documentation, https://github.com/OuOHoon/tistory-indexer#readme
Project-URL: Issues, https://github.com/OuOHoon/tistory-indexer/issues
Project-URL: Source, https://github.com/OuOHoon/tistory-indexer
Author-email: OuOHoon <begreat@kakao.com>
License-Expression: MIT
License-File: LICENSE
Keywords: blog,indexing,tistory
Classifier: Development Status :: 4 - Beta
Classifier: License :: OSI Approved :: MIT License
Classifier: Programming Language :: Python
Classifier: Programming Language :: Python :: 3.11
Classifier: Programming Language :: Python :: 3.12
Classifier: Programming Language :: Python :: Implementation :: CPython
Classifier: Programming Language :: Python :: Implementation :: PyPy
Requires-Python: >=3.11
Requires-Dist: beautifulsoup4
Requires-Dist: google-auth
Requires-Dist: google-auth-oauthlib
Requires-Dist: lxml
Requires-Dist: requests
